dataqualitycheck/__init__.py
dataqualitycheck/commonutilities.py
dataqualitycheck/consistencycheck.py
dataqualitycheck/dataprofile.py
dataqualitycheck/singledatasetqualitycheck.py
dataqualitycheck/singledatasetqualitycheckpolars.py
dataqualitycheck/singledatasetqualitycheckspark.py
dataqualitycheck/datasources/azureblobdf.py
dataqualitycheck/datasources/commonutilities.py
dataqualitycheck/datasources/databricksfilesystemdf.py
dataqualitycheck/datasources/databrickssqldf.py
dataqualitycheck/datasources/localfilesystemdf.py
dq_module-1.0.0.dist-info/METADATA
dq_module-1.0.0.dist-info/WHEEL
dq_module-1.0.0.dist-info/top_level.txt
dq_module-1.0.0.dist-info/RECORD
